juphelper/__init__.py
juphelper/helper.py
juphelper-0.1.6.dist-info/METADATA
juphelper-0.1.6.dist-info/WHEEL
juphelper-0.1.6.dist-info/entry_points.txt
juphelper-0.1.6.dist-info/top_level.txt
juphelper-0.1.6.dist-info/RECORD
